{
  "324013PD": {
    "width": 639.0,
    "thumb_url": "http://purl.slwa.wa.gov.au/slwa_b3373468_2.png",
    "image_url": "http://purl.slwa.wa.gov.au/slwa_b3373468_2.jpg",
    "date": "1986-04-16",
    "height": 760.0,
    "text": null,
    "years": [
      1986.0
    ],
    "folder": null,
    "original_title": "",
    "title": "Hair styles modelled for the Associates Hair Salon & Academy, 331 Murray Street, Perth, 16 April 1986"
  },
  "325733PD": {
    "width": 596.0,
    "thumb_url": "http://purl.slwa.wa.gov.au/slwa_b3373468_4.png",
    "image_url": "http://purl.slwa.wa.gov.au/slwa_b3373468_4.jpg",
    "date": "1986-04-16",
    "height": 760.0,
    "text": null,
    "years": [
      1986.0
    ],
    "folder": null,
    "original_title": "",
    "title": "Hair styles modelled for the Associates Hair Salon & Academy, 331 Murray Street, Perth, 16 April 1986"
  },
  "325734PD": {
    "width": 574.0,
    "thumb_url": "http://purl.slwa.wa.gov.au/slwa_b3373468_5.png",
    "image_url": "http://purl.slwa.wa.gov.au/slwa_b3373468_5.jpg",
    "date": "1986-04-16",
    "height": 760.0,
    "text": null,
    "years": [
      1986.0
    ],
    "folder": null,
    "original_title": "",
    "title": "Hair styles modelled for the Associates Hair Salon & Academy, 331 Murray Street, Perth, 16 April 1986"
  },
  "324014PD": {
    "width": 639.0,
    "thumb_url": "http://purl.slwa.wa.gov.au/slwa_b3373468_3.png",
    "image_url": "http://purl.slwa.wa.gov.au/slwa_b3373468_3.jpg",
    "date": "1986-04-16",
    "height": 760.0,
    "text": null,
    "years": [
      1986.0
    ],
    "folder": null,
    "original_title": "",
    "title": "Hair styles modelled for the Associates Hair Salon & Academy, 331 Murray Street, Perth, 16 April 1986"
  },
  "324012PD": {
    "width": 639.0,
    "thumb_url": "http://purl.slwa.wa.gov.au/slwa_b3373468_1.png",
    "image_url": "http://purl.slwa.wa.gov.au/slwa_b3373468_1.jpg",
    "date": "1986-04-16",
    "height": 760.0,
    "text": null,
    "years": [
      1986.0
    ],
    "folder": null,
    "original_title": "",
    "title": "Hair styles modelled for the Associates Hair Salon & Academy, 331 Murray Street, Perth, 16 April 1986"
  }
}